<?xml version="1.0" encoding="utf-8" ?>
<dwsync>
<file name="menu.htm" server="www.kriyayogadebabaji.net/httpdocs/" local="129840610277187500" remote="129840610200000000" />
<file name="18 Siddhas.doc" server="www.kriyayogadebabaji.net/httpdocs/" local="129810494278430000" remote="129810494400000000" />
<file name="18 Siddhas.pdf" server="www.kriyayogadebabaji.net/httpdocs/" local="129810494540937500" remote="129810494400000000" />
<file name="samadhi.doc" server="www.kriyayogadebabaji.net/httpdocs/" local="129810490645930000" remote="129810491400000000" />
<file name="samadhi.pdf" server="www.kriyayogadebabaji.net/httpdocs/" local="129810490741562500" remote="129810491400000000" />
<file name="luz.doc" server="www.kriyayogadebabaji.net/httpdocs/" local="129815690330460000" remote="129815692200000000" />
<file name="luz.pdf" server="www.kriyayogadebabaji.net/httpdocs/" local="129815690456562500" remote="129815692200000000" />
<file name="OM.doc" server="www.kriyayogadebabaji.net/httpdocs/" local="129840580306870000" remote="129840580200000000" />
<file name="OM.pdf" server="www.kriyayogadebabaji.net/httpdocs/" local="129840580455156250" remote="129840580200000000" />
<file name="139.doc" server="www.kriyayogadebabaji.net/httpdocs/" local="129840613494530000" remote="129840613800000000" />
<file name="139.pdf" server="www.kriyayogadebabaji.net/httpdocs/" local="129840613607343750" remote="129840613800000000" />
</dwsync>